mcpnacos_config/__init__.py
mcpnacos_config/dev_test.py
mcpnacos_config/main.py
mcpnacos_config/mcpnacos_config-wrapper.py
nacos_config_mcp-0.1.15.dist-info/METADATA
nacos_config_mcp-0.1.15.dist-info/WHEEL
nacos_config_mcp-0.1.15.dist-info/entry_points.txt
nacos_config_mcp-0.1.15.dist-info/RECORD
