Metadata-Version: 2.4
Name: nacos-config-mcp
Version: 0.1.15
Summary: Nacos Config MCP - manage Nacos configuration servers for debugging
Author-email: czyhandsome <czyhandsome@foxmail.com>
License: MIT
Keywords: config,mcp,nacos,protocol,server
Requires-Python: >=3.12
Requires-Dist: mcp-python>=0.1.4
Requires-Dist: nacos-sdk-python>=2.0.3
Requires-Dist: requests>=2.32.0
